pycatcher/__init__.py
pycatcher/api_catch.py
pycatcher/api_diagnostics.py
pycatcher/api_run.py
pycatcher/catch.py
pycatcher/diagnostics.py
pycatcher/templates/index.html
pycatcher/webapp.py
pycatcher-0.0.72.dist-info/LICENSE
pycatcher-0.0.72.dist-info/METADATA
pycatcher-0.0.72.dist-info/WHEEL
pycatcher-0.0.72.dist-info/entry_points.txt
pycatcher-0.0.72.dist-info/RECORD
