Metadata-Version: 2.3
Name: pycatcher
Version: 0.0.72
Summary: This package identifies outlier(s) for a given time-series dataset in simple steps. It supports day, week, month and quarter level time-series data.
License: MIT
Keywords: outlier-detection,python,timeseries
Author: Aseem Anand
Author-email: aseemanand@gmail.com
Maintainer: Jagadish Pamarthi/Uday Kuchimanchi/Aadya Anand
Requires-Python: >=3.9,<4.0
Classifier: License :: OSI Approved :: MIT License
Classifier: Operating System :: OS Independent
Classifier: Programming Language :: Python :: 3
Classifier: Programming Language :: Python :: 3.9
Classifier: Programming Language :: Python :: 3.10
Classifier: Programming Language :: Python :: 3.11
Classifier: Programming Language :: Python :: 3.12
Classifier: Programming Language :: Python :: 3.13
Requires-Dist: flask (>=3.1.0,<4.0.0)
Requires-Dist: mkdocs (>=1.5.0,<2.0.0)
Requires-Dist: mkdocs-material (>=9.1.3,<10.0.0)
Requires-Dist: numpy (>=1.24.0,<2.0.0)
Requires-Dist: pandas (>=2.0.0,<3.0.0)
Requires-Dist: pyod (>=2.0.0,<3.0.0)
Requires-Dist: pyspark (>=3.3.0,<4.0.0)
Requires-Dist: scikit-learn (>=1.3.0,<2.0.0)
Requires-Dist: scipy (>=1.9.0,<1.14.0)
Requires-Dist: seaborn (>=0.13.0,<0.14.0)
Requires-Dist: sesd (>=0.2.0,<0.3.0)
Requires-Dist: statsmodels (==0.14.4)
Project-URL: Repository, https://github.com/aseemanand/pycatcher/
